lazy_module/__init__.py
lazy_module/_modidx.py
lazy_module/core.py
lazy_module-0.0.3.dist-info/LICENSE
lazy_module-0.0.3.dist-info/METADATA
lazy_module-0.0.3.dist-info/WHEEL
lazy_module-0.0.3.dist-info/entry_points.txt
lazy_module-0.0.3.dist-info/top_level.txt
lazy_module-0.0.3.dist-info/RECORD
