Metadata-Version: 2.1
Name: lazy-module
Version: 0.0.3
Summary: Python LazyModule to replace python import statement for fast import
Home-page: https://github.com/anhvth/lazy_module/
Author: anhvth
Author-email: anhvth.226@gmail.com
License: Apache Software License 2.0
Keywords: Python LazyModule
Platform: UNKNOWN
Classifier: Development Status :: 3 - Alpha
Classifier: Intended Audience :: Developers
Classifier: Natural Language :: English
Classifier: Programming Language :: Python :: 3.5
Classifier: Programming Language :: Python :: 3.6
Classifier: Programming Language :: Python :: 3.7
Classifier: Programming Language :: Python :: 3.8
Classifier: Programming Language :: Python :: 3.9
Classifier: Programming Language :: Python :: 3.10
Classifier: License :: OSI Approved :: Apache Software License
Requires-Python: >=3.5
Provides-Extra: dev
